{
  "background_color": "#6495ed",
  "description": "Social Science 43: A student-run blog exploring economics, philosophy, and society.",
  "dir": "ltr",
  "display": "standalone",
  "name": "Social Science 43",
  "orientation": "portrait",
  "scope": "/",
  "short_name": "SS43",
  "start_url": "/",
  "theme_color": "#0a192f",
  "icons": [
    {
      "src": "https://socialscience43.github.io/IMG_1624.png",
      "type": "image/png",
      "sizes": "1035x1080",
      "isSquare": false,
      "isPng": true,
      "isWebp": false,
      "isJpg": false,
      "width": 1035,
      "is512x512": false,
      "is256x256": false,
      "is192x192": false
    },
    {
      "src": "https://socialscience43.github.io/docs/social-science-43-banner.png",
      "isSquare": false,
      "isPng": true,
      "isWebp": false,
      "isJpg": false,
      "width": 0,
      "is512x512": false,
      "is256x256": false,
      "is192x192": false
    }
  ],
  "id": "/",
  "lang": "en",
  "categories": [
    "business",
    "entertainment",
    "events",
    "lifestyle",
    "news",
    "politics"
  ],
  "display_override": [
    "window-controls-overlay",
    "fullscreen"
  ]
}